Metadata-Version: 2.1
Name: jkx
Version: 1.0.4
Summary: UNKNOWN
Home-page: https://github.com/AndrewHeaney/json-key-explorer
Author: Andrew Heaney
Author-email: heaneyandrew11@gmail.com
License: MIT
Keywords: json
Platform: UNKNOWN
License-File: LICENSE.txt
